[ {
  "id" : 992435760,
  "url" : "https://api.github.com/repos/hzuapps/android-labs-2017/issues/events/992435760",
  "actor" : {
    "login" : "xiemz",
    "id" : 26158948,
    "avatar_url" : "https://avatars3.githubusercontent.com/u/26158948?v=3",
    "gravatar_id" : "",
    "url" : "https://api.github.com/users/xiemz",
    "html_url" : "https://github.com/xiemz",
    "followers_url" : "https://api.github.com/users/xiemz/followers",
    "following_url" : "https://api.github.com/users/xiemz/following{/other_user}",
    "gists_url" : "https://api.github.com/users/xiemz/gists{/gist_id}",
    "starred_url" : "https://api.github.com/users/xiemz/starred{/owner}{/repo}",
    "subscriptions_url" : "https://api.github.com/users/xiemz/subscriptions",
    "organizations_url" : "https://api.github.com/users/xiemz/orgs",
    "repos_url" : "https://api.github.com/users/xiemz/repos",
    "events_url" : "https://api.github.com/users/xiemz/events{/privacy}",
    "received_events_url" : "https://api.github.com/users/xiemz/received_events",
    "type" : "User",
    "site_admin" : false
  },
  "event" : "referenced",
  "commit_id" : "dda15af1d760dbbf327527cf6b3f1316389a049e",
  "commit_url" : "https://api.github.com/repos/xiemz/android-labs-2017/commits/dda15af1d760dbbf327527cf6b3f1316389a049e",
  "created_at" : "2017-03-09T02:21:05Z"
}, {
  "id" : 992455832,
  "url" : "https://api.github.com/repos/hzuapps/android-labs-2017/issues/events/992455832",
  "actor" : {
    "login" : "zengsn",
    "id" : 627946,
    "avatar_url" : "https://avatars1.githubusercontent.com/u/627946?v=3",
    "gravatar_id" : "",
    "url" : "https://api.github.com/users/zengsn",
    "html_url" : "https://github.com/zengsn",
    "followers_url" : "https://api.github.com/users/zengsn/followers",
    "following_url" : "https://api.github.com/users/zengsn/following{/other_user}",
    "gists_url" : "https://api.github.com/users/zengsn/gists{/gist_id}",
    "starred_url" : "https://api.github.com/users/zengsn/starred{/owner}{/repo}",
    "subscriptions_url" : "https://api.github.com/users/zengsn/subscriptions",
    "organizations_url" : "https://api.github.com/users/zengsn/orgs",
    "repos_url" : "https://api.github.com/users/zengsn/repos",
    "events_url" : "https://api.github.com/users/zengsn/events{/privacy}",
    "received_events_url" : "https://api.github.com/users/zengsn/received_events",
    "type" : "User",
    "site_admin" : false
  },
  "event" : "referenced",
  "commit_id" : "4c7958464ceffbc08b37e95e69874a12dd972968",
  "commit_url" : "https://api.github.com/repos/hzuapps/android-labs-2017/commits/4c7958464ceffbc08b37e95e69874a12dd972968",
  "created_at" : "2017-03-09T02:47:04Z"
}, {
  "id" : 1141548782,
  "url" : "https://api.github.com/repos/hzuapps/android-labs-2017/issues/events/1141548782",
  "actor" : {
    "login" : "zengsn",
    "id" : 627946,
    "avatar_url" : "https://avatars1.githubusercontent.com/u/627946?v=3",
    "gravatar_id" : "",
    "url" : "https://api.github.com/users/zengsn",
    "html_url" : "https://github.com/zengsn",
    "followers_url" : "https://api.github.com/users/zengsn/followers",
    "following_url" : "https://api.github.com/users/zengsn/following{/other_user}",
    "gists_url" : "https://api.github.com/users/zengsn/gists{/gist_id}",
    "starred_url" : "https://api.github.com/users/zengsn/starred{/owner}{/repo}",
    "subscriptions_url" : "https://api.github.com/users/zengsn/subscriptions",
    "organizations_url" : "https://api.github.com/users/zengsn/orgs",
    "repos_url" : "https://api.github.com/users/zengsn/repos",
    "events_url" : "https://api.github.com/users/zengsn/events{/privacy}",
    "received_events_url" : "https://api.github.com/users/zengsn/received_events",
    "type" : "User",
    "site_admin" : false
  },
  "event" : "closed",
  "commit_id" : null,
  "commit_url" : null,
  "created_at" : "2017-06-28T01:00:21Z"
}, {
  "id" : 1141549388,
  "url" : "https://api.github.com/repos/hzuapps/android-labs-2017/issues/events/1141549388",
  "actor" : {
    "login" : "zengsn",
    "id" : 627946,
    "avatar_url" : "https://avatars1.githubusercontent.com/u/627946?v=3",
    "gravatar_id" : "",
    "url" : "https://api.github.com/users/zengsn",
    "html_url" : "https://github.com/zengsn",
    "followers_url" : "https://api.github.com/users/zengsn/followers",
    "following_url" : "https://api.github.com/users/zengsn/following{/other_user}",
    "gists_url" : "https://api.github.com/users/zengsn/gists{/gist_id}",
    "starred_url" : "https://api.github.com/users/zengsn/starred{/owner}{/repo}",
    "subscriptions_url" : "https://api.github.com/users/zengsn/subscriptions",
    "organizations_url" : "https://api.github.com/users/zengsn/orgs",
    "repos_url" : "https://api.github.com/users/zengsn/repos",
    "events_url" : "https://api.github.com/users/zengsn/events{/privacy}",
    "received_events_url" : "https://api.github.com/users/zengsn/received_events",
    "type" : "User",
    "site_admin" : false
  },
  "event" : "reopened",
  "commit_id" : null,
  "commit_url" : null,
  "created_at" : "2017-06-28T01:01:14Z"
} ]