[ {
  "id" : 968297561,
  "url" : "https://api.github.com/repos/hzuapps/android-labs-2017/issues/events/968297561",
  "actor" : {
    "login" : "zengsn",
    "id" : 627946,
    "avatar_url" : "https://avatars1.githubusercontent.com/u/627946?v=3",
    "gravatar_id" : "",
    "url" : "https://api.github.com/users/zengsn",
    "html_url" : "https://github.com/zengsn",
    "followers_url" : "https://api.github.com/users/zengsn/followers",
    "following_url" : "https://api.github.com/users/zengsn/following{/other_user}",
    "gists_url" : "https://api.github.com/users/zengsn/gists{/gist_id}",
    "starred_url" : "https://api.github.com/users/zengsn/starred{/owner}{/repo}",
    "subscriptions_url" : "https://api.github.com/users/zengsn/subscriptions",
    "organizations_url" : "https://api.github.com/users/zengsn/orgs",
    "repos_url" : "https://api.github.com/users/zengsn/repos",
    "events_url" : "https://api.github.com/users/zengsn/events{/privacy}",
    "received_events_url" : "https://api.github.com/users/zengsn/received_events",
    "type" : "User",
    "site_admin" : false
  },
  "event" : "labeled",
  "commit_id" : null,
  "commit_url" : null,
  "created_at" : "2017-02-19T12:08:14Z",
  "label" : {
    "name" : "实验",
    "color" : "ee0701"
  }
}, {
  "id" : 1098263718,
  "url" : "https://api.github.com/repos/hzuapps/android-labs-2017/issues/events/1098263718",
  "actor" : {
    "login" : "shezhiming",
    "id" : 13965087,
    "avatar_url" : "https://avatars0.githubusercontent.com/u/13965087?v=3",
    "gravatar_id" : "",
    "url" : "https://api.github.com/users/shezhiming",
    "html_url" : "https://github.com/shezhiming",
    "followers_url" : "https://api.github.com/users/shezhiming/followers",
    "following_url" : "https://api.github.com/users/shezhiming/following{/other_user}",
    "gists_url" : "https://api.github.com/users/shezhiming/gists{/gist_id}",
    "starred_url" : "https://api.github.com/users/shezhiming/starred{/owner}{/repo}",
    "subscriptions_url" : "https://api.github.com/users/shezhiming/subscriptions",
    "organizations_url" : "https://api.github.com/users/shezhiming/orgs",
    "repos_url" : "https://api.github.com/users/shezhiming/repos",
    "events_url" : "https://api.github.com/users/shezhiming/events{/privacy}",
    "received_events_url" : "https://api.github.com/users/shezhiming/received_events",
    "type" : "User",
    "site_admin" : false
  },
  "event" : "referenced",
  "commit_id" : "0801216cdece33a35ab70cd0cc0ac0817d4bcefb",
  "commit_url" : "https://api.github.com/repos/shezhiming/android-labs-2017/commits/0801216cdece33a35ab70cd0cc0ac0817d4bcefb",
  "created_at" : "2017-05-26T01:54:15Z"
}, {
  "id" : 1099816239,
  "url" : "https://api.github.com/repos/hzuapps/android-labs-2017/issues/events/1099816239",
  "actor" : {
    "login" : "shezhiming",
    "id" : 13965087,
    "avatar_url" : "https://avatars0.githubusercontent.com/u/13965087?v=3",
    "gravatar_id" : "",
    "url" : "https://api.github.com/users/shezhiming",
    "html_url" : "https://github.com/shezhiming",
    "followers_url" : "https://api.github.com/users/shezhiming/followers",
    "following_url" : "https://api.github.com/users/shezhiming/following{/other_user}",
    "gists_url" : "https://api.github.com/users/shezhiming/gists{/gist_id}",
    "starred_url" : "https://api.github.com/users/shezhiming/starred{/owner}{/repo}",
    "subscriptions_url" : "https://api.github.com/users/shezhiming/subscriptions",
    "organizations_url" : "https://api.github.com/users/shezhiming/orgs",
    "repos_url" : "https://api.github.com/users/shezhiming/repos",
    "events_url" : "https://api.github.com/users/shezhiming/events{/privacy}",
    "received_events_url" : "https://api.github.com/users/shezhiming/received_events",
    "type" : "User",
    "site_admin" : false
  },
  "event" : "referenced",
  "commit_id" : "2eb5bb134b0df65e3c0412ae2fd3bb354ad064ee",
  "commit_url" : "https://api.github.com/repos/shezhiming/android-labs-2017/commits/2eb5bb134b0df65e3c0412ae2fd3bb354ad064ee",
  "created_at" : "2017-05-27T07:45:09Z"
}, {
  "id" : 1099816241,
  "url" : "https://api.github.com/repos/hzuapps/android-labs-2017/issues/events/1099816241",
  "actor" : {
    "login" : "shezhiming",
    "id" : 13965087,
    "avatar_url" : "https://avatars0.githubusercontent.com/u/13965087?v=3",
    "gravatar_id" : "",
    "url" : "https://api.github.com/users/shezhiming",
    "html_url" : "https://github.com/shezhiming",
    "followers_url" : "https://api.github.com/users/shezhiming/followers",
    "following_url" : "https://api.github.com/users/shezhiming/following{/other_user}",
    "gists_url" : "https://api.github.com/users/shezhiming/gists{/gist_id}",
    "starred_url" : "https://api.github.com/users/shezhiming/starred{/owner}{/repo}",
    "subscriptions_url" : "https://api.github.com/users/shezhiming/subscriptions",
    "organizations_url" : "https://api.github.com/users/shezhiming/orgs",
    "repos_url" : "https://api.github.com/users/shezhiming/repos",
    "events_url" : "https://api.github.com/users/shezhiming/events{/privacy}",
    "received_events_url" : "https://api.github.com/users/shezhiming/received_events",
    "type" : "User",
    "site_admin" : false
  },
  "event" : "referenced",
  "commit_id" : "e242e080ff2041054f30e82d7b6c09fbb8ade902",
  "commit_url" : "https://api.github.com/repos/shezhiming/android-labs-2017/commits/e242e080ff2041054f30e82d7b6c09fbb8ade902",
  "created_at" : "2017-05-27T07:45:09Z"
}, {
  "id" : 1100052639,
  "url" : "https://api.github.com/repos/hzuapps/android-labs-2017/issues/events/1100052639",
  "actor" : {
    "login" : "zengsn",
    "id" : 627946,
    "avatar_url" : "https://avatars1.githubusercontent.com/u/627946?v=3",
    "gravatar_id" : "",
    "url" : "https://api.github.com/users/zengsn",
    "html_url" : "https://github.com/zengsn",
    "followers_url" : "https://api.github.com/users/zengsn/followers",
    "following_url" : "https://api.github.com/users/zengsn/following{/other_user}",
    "gists_url" : "https://api.github.com/users/zengsn/gists{/gist_id}",
    "starred_url" : "https://api.github.com/users/zengsn/starred{/owner}{/repo}",
    "subscriptions_url" : "https://api.github.com/users/zengsn/subscriptions",
    "organizations_url" : "https://api.github.com/users/zengsn/orgs",
    "repos_url" : "https://api.github.com/users/zengsn/repos",
    "events_url" : "https://api.github.com/users/zengsn/events{/privacy}",
    "received_events_url" : "https://api.github.com/users/zengsn/received_events",
    "type" : "User",
    "site_admin" : false
  },
  "event" : "referenced",
  "commit_id" : "04afc00bccc84846858d0f30628c74c7ad0e4811",
  "commit_url" : "https://api.github.com/repos/hzuapps/android-labs-2017/commits/04afc00bccc84846858d0f30628c74c7ad0e4811",
  "created_at" : "2017-05-28T01:47:30Z"
}, {
  "id" : 1101864491,
  "url" : "https://api.github.com/repos/hzuapps/android-labs-2017/issues/events/1101864491",
  "actor" : {
    "login" : "hizzj",
    "id" : 19361617,
    "avatar_url" : "https://avatars1.githubusercontent.com/u/19361617?v=3",
    "gravatar_id" : "",
    "url" : "https://api.github.com/users/hizzj",
    "html_url" : "https://github.com/hizzj",
    "followers_url" : "https://api.github.com/users/hizzj/followers",
    "following_url" : "https://api.github.com/users/hizzj/following{/other_user}",
    "gists_url" : "https://api.github.com/users/hizzj/gists{/gist_id}",
    "starred_url" : "https://api.github.com/users/hizzj/starred{/owner}{/repo}",
    "subscriptions_url" : "https://api.github.com/users/hizzj/subscriptions",
    "organizations_url" : "https://api.github.com/users/hizzj/orgs",
    "repos_url" : "https://api.github.com/users/hizzj/repos",
    "events_url" : "https://api.github.com/users/hizzj/events{/privacy}",
    "received_events_url" : "https://api.github.com/users/hizzj/received_events",
    "type" : "User",
    "site_admin" : false
  },
  "event" : "referenced",
  "commit_id" : "0b342a4c3f12f783b360561a68b74d9354ff7374",
  "commit_url" : "https://api.github.com/repos/hizzj/android-labs-2017/commits/0b342a4c3f12f783b360561a68b74d9354ff7374",
  "created_at" : "2017-05-30T08:27:24Z"
}, {
  "id" : 1104301733,
  "url" : "https://api.github.com/repos/hzuapps/android-labs-2017/issues/events/1104301733",
  "actor" : {
    "login" : "zengsn",
    "id" : 627946,
    "avatar_url" : "https://avatars1.githubusercontent.com/u/627946?v=3",
    "gravatar_id" : "",
    "url" : "https://api.github.com/users/zengsn",
    "html_url" : "https://github.com/zengsn",
    "followers_url" : "https://api.github.com/users/zengsn/followers",
    "following_url" : "https://api.github.com/users/zengsn/following{/other_user}",
    "gists_url" : "https://api.github.com/users/zengsn/gists{/gist_id}",
    "starred_url" : "https://api.github.com/users/zengsn/starred{/owner}{/repo}",
    "subscriptions_url" : "https://api.github.com/users/zengsn/subscriptions",
    "organizations_url" : "https://api.github.com/users/zengsn/orgs",
    "repos_url" : "https://api.github.com/users/zengsn/repos",
    "events_url" : "https://api.github.com/users/zengsn/events{/privacy}",
    "received_events_url" : "https://api.github.com/users/zengsn/received_events",
    "type" : "User",
    "site_admin" : false
  },
  "event" : "referenced",
  "commit_id" : "bba68f4e3110a15d4fb2134b5700bb7f331d1253",
  "commit_url" : "https://api.github.com/repos/hzuapps/android-labs-2017/commits/bba68f4e3110a15d4fb2134b5700bb7f331d1253",
  "created_at" : "2017-05-31T14:39:37Z"
}, {
  "id" : 1105961704,
  "url" : "https://api.github.com/repos/hzuapps/android-labs-2017/issues/events/1105961704",
  "actor" : {
    "login" : "JCLin0318",
    "id" : 26159058,
    "avatar_url" : "https://avatars3.githubusercontent.com/u/26159058?v=3",
    "gravatar_id" : "",
    "url" : "https://api.github.com/users/JCLin0318",
    "html_url" : "https://github.com/JCLin0318",
    "followers_url" : "https://api.github.com/users/JCLin0318/followers",
    "following_url" : "https://api.github.com/users/JCLin0318/following{/other_user}",
    "gists_url" : "https://api.github.com/users/JCLin0318/gists{/gist_id}",
    "starred_url" : "https://api.github.com/users/JCLin0318/starred{/owner}{/repo}",
    "subscriptions_url" : "https://api.github.com/users/JCLin0318/subscriptions",
    "organizations_url" : "https://api.github.com/users/JCLin0318/orgs",
    "repos_url" : "https://api.github.com/users/JCLin0318/repos",
    "events_url" : "https://api.github.com/users/JCLin0318/events{/privacy}",
    "received_events_url" : "https://api.github.com/users/JCLin0318/received_events",
    "type" : "User",
    "site_admin" : false
  },
  "event" : "referenced",
  "commit_id" : "1dbb2469e746a46d0ecd86b9d3ca2ec4d9152965",
  "commit_url" : "https://api.github.com/repos/JCLin0318/android-labs-2017/commits/1dbb2469e746a46d0ecd86b9d3ca2ec4d9152965",
  "created_at" : "2017-06-01T12:43:35Z"
}, {
  "id" : 1107290281,
  "url" : "https://api.github.com/repos/hzuapps/android-labs-2017/issues/events/1107290281",
  "actor" : {
    "login" : "zengsn",
    "id" : 627946,
    "avatar_url" : "https://avatars1.githubusercontent.com/u/627946?v=3",
    "gravatar_id" : "",
    "url" : "https://api.github.com/users/zengsn",
    "html_url" : "https://github.com/zengsn",
    "followers_url" : "https://api.github.com/users/zengsn/followers",
    "following_url" : "https://api.github.com/users/zengsn/following{/other_user}",
    "gists_url" : "https://api.github.com/users/zengsn/gists{/gist_id}",
    "starred_url" : "https://api.github.com/users/zengsn/starred{/owner}{/repo}",
    "subscriptions_url" : "https://api.github.com/users/zengsn/subscriptions",
    "organizations_url" : "https://api.github.com/users/zengsn/orgs",
    "repos_url" : "https://api.github.com/users/zengsn/repos",
    "events_url" : "https://api.github.com/users/zengsn/events{/privacy}",
    "received_events_url" : "https://api.github.com/users/zengsn/received_events",
    "type" : "User",
    "site_admin" : false
  },
  "event" : "referenced",
  "commit_id" : "7b478494c0861e17bbe1dd983d4824e861e9b094",
  "commit_url" : "https://api.github.com/repos/hzuapps/android-labs-2017/commits/7b478494c0861e17bbe1dd983d4824e861e9b094",
  "created_at" : "2017-06-02T06:59:09Z"
}, {
  "id" : 1107933581,
  "url" : "https://api.github.com/repos/hzuapps/android-labs-2017/issues/events/1107933581",
  "actor" : {
    "login" : "mokulai",
    "id" : 14102144,
    "avatar_url" : "https://avatars3.githubusercontent.com/u/14102144?v=3",
    "gravatar_id" : "",
    "url" : "https://api.github.com/users/mokulai",
    "html_url" : "https://github.com/mokulai",
    "followers_url" : "https://api.github.com/users/mokulai/followers",
    "following_url" : "https://api.github.com/users/mokulai/following{/other_user}",
    "gists_url" : "https://api.github.com/users/mokulai/gists{/gist_id}",
    "starred_url" : "https://api.github.com/users/mokulai/starred{/owner}{/repo}",
    "subscriptions_url" : "https://api.github.com/users/mokulai/subscriptions",
    "organizations_url" : "https://api.github.com/users/mokulai/orgs",
    "repos_url" : "https://api.github.com/users/mokulai/repos",
    "events_url" : "https://api.github.com/users/mokulai/events{/privacy}",
    "received_events_url" : "https://api.github.com/users/mokulai/received_events",
    "type" : "User",
    "site_admin" : false
  },
  "event" : "referenced",
  "commit_id" : "2092bda83e1e88ff73c7d9ea86664195bfef1da4",
  "commit_url" : "https://api.github.com/repos/mokulai/android-labs-2017/commits/2092bda83e1e88ff73c7d9ea86664195bfef1da4",
  "created_at" : "2017-06-02T14:44:22Z"
}, {
  "id" : 1108076036,
  "url" : "https://api.github.com/repos/hzuapps/android-labs-2017/issues/events/1108076036",
  "actor" : {
    "login" : "mokulai",
    "id" : 14102144,
    "avatar_url" : "https://avatars3.githubusercontent.com/u/14102144?v=3",
    "gravatar_id" : "",
    "url" : "https://api.github.com/users/mokulai",
    "html_url" : "https://github.com/mokulai",
    "followers_url" : "https://api.github.com/users/mokulai/followers",
    "following_url" : "https://api.github.com/users/mokulai/following{/other_user}",
    "gists_url" : "https://api.github.com/users/mokulai/gists{/gist_id}",
    "starred_url" : "https://api.github.com/users/mokulai/starred{/owner}{/repo}",
    "subscriptions_url" : "https://api.github.com/users/mokulai/subscriptions",
    "organizations_url" : "https://api.github.com/users/mokulai/orgs",
    "repos_url" : "https://api.github.com/users/mokulai/repos",
    "events_url" : "https://api.github.com/users/mokulai/events{/privacy}",
    "received_events_url" : "https://api.github.com/users/mokulai/received_events",
    "type" : "User",
    "site_admin" : false
  },
  "event" : "referenced",
  "commit_id" : "ed5f82def88f5ad5e5c6fba219b3ed2d821a50d9",
  "commit_url" : "https://api.github.com/repos/mokulai/android-labs-2017/commits/ed5f82def88f5ad5e5c6fba219b3ed2d821a50d9",
  "created_at" : "2017-06-02T16:06:57Z"
}, {
  "id" : 1108698610,
  "url" : "https://api.github.com/repos/hzuapps/android-labs-2017/issues/events/1108698610",
  "actor" : {
    "login" : "LittleUncle",
    "id" : 26004267,
    "avatar_url" : "https://avatars1.githubusercontent.com/u/26004267?v=3",
    "gravatar_id" : "",
    "url" : "https://api.github.com/users/LittleUncle",
    "html_url" : "https://github.com/LittleUncle",
    "followers_url" : "https://api.github.com/users/LittleUncle/followers",
    "following_url" : "https://api.github.com/users/LittleUncle/following{/other_user}",
    "gists_url" : "https://api.github.com/users/LittleUncle/gists{/gist_id}",
    "starred_url" : "https://api.github.com/users/LittleUncle/starred{/owner}{/repo}",
    "subscriptions_url" : "https://api.github.com/users/LittleUncle/subscriptions",
    "organizations_url" : "https://api.github.com/users/LittleUncle/orgs",
    "repos_url" : "https://api.github.com/users/LittleUncle/repos",
    "events_url" : "https://api.github.com/users/LittleUncle/events{/privacy}",
    "received_events_url" : "https://api.github.com/users/LittleUncle/received_events",
    "type" : "User",
    "site_admin" : false
  },
  "event" : "referenced",
  "commit_id" : "096ad7680cd265c4d148d537fe6a2fe51740e9ba",
  "commit_url" : "https://api.github.com/repos/LittleUncle/android-labs-2017/commits/096ad7680cd265c4d148d537fe6a2fe51740e9ba",
  "created_at" : "2017-06-03T02:08:42Z"
}, {
  "id" : 1108767251,
  "url" : "https://api.github.com/repos/hzuapps/android-labs-2017/issues/events/1108767251",
  "actor" : {
    "login" : "LittleUncle",
    "id" : 26004267,
    "avatar_url" : "https://avatars1.githubusercontent.com/u/26004267?v=3",
    "gravatar_id" : "",
    "url" : "https://api.github.com/users/LittleUncle",
    "html_url" : "https://github.com/LittleUncle",
    "followers_url" : "https://api.github.com/users/LittleUncle/followers",
    "following_url" : "https://api.github.com/users/LittleUncle/following{/other_user}",
    "gists_url" : "https://api.github.com/users/LittleUncle/gists{/gist_id}",
    "starred_url" : "https://api.github.com/users/LittleUncle/starred{/owner}{/repo}",
    "subscriptions_url" : "https://api.github.com/users/LittleUncle/subscriptions",
    "organizations_url" : "https://api.github.com/users/LittleUncle/orgs",
    "repos_url" : "https://api.github.com/users/LittleUncle/repos",
    "events_url" : "https://api.github.com/users/LittleUncle/events{/privacy}",
    "received_events_url" : "https://api.github.com/users/LittleUncle/received_events",
    "type" : "User",
    "site_admin" : false
  },
  "event" : "referenced",
  "commit_id" : "a9f75a0ddbd86f915cf2a41ee0a9248ff7332efd",
  "commit_url" : "https://api.github.com/repos/LittleUncle/android-labs-2017/commits/a9f75a0ddbd86f915cf2a41ee0a9248ff7332efd",
  "created_at" : "2017-06-03T07:30:24Z"
}, {
  "id" : 1108768132,
  "url" : "https://api.github.com/repos/hzuapps/android-labs-2017/issues/events/1108768132",
  "actor" : {
    "login" : "LittleUncle",
    "id" : 26004267,
    "avatar_url" : "https://avatars1.githubusercontent.com/u/26004267?v=3",
    "gravatar_id" : "",
    "url" : "https://api.github.com/users/LittleUncle",
    "html_url" : "https://github.com/LittleUncle",
    "followers_url" : "https://api.github.com/users/LittleUncle/followers",
    "following_url" : "https://api.github.com/users/LittleUncle/following{/other_user}",
    "gists_url" : "https://api.github.com/users/LittleUncle/gists{/gist_id}",
    "starred_url" : "https://api.github.com/users/LittleUncle/starred{/owner}{/repo}",
    "subscriptions_url" : "https://api.github.com/users/LittleUncle/subscriptions",
    "organizations_url" : "https://api.github.com/users/LittleUncle/orgs",
    "repos_url" : "https://api.github.com/users/LittleUncle/repos",
    "events_url" : "https://api.github.com/users/LittleUncle/events{/privacy}",
    "received_events_url" : "https://api.github.com/users/LittleUncle/received_events",
    "type" : "User",
    "site_admin" : false
  },
  "event" : "referenced",
  "commit_id" : "dfa1ab48179d07bf1fcf2b0fcac49e63e6e85d21",
  "commit_url" : "https://api.github.com/repos/LittleUncle/android-labs-2017/commits/dfa1ab48179d07bf1fcf2b0fcac49e63e6e85d21",
  "created_at" : "2017-06-03T07:35:09Z"
}, {
  "id" : 1108801928,
  "url" : "https://api.github.com/repos/hzuapps/android-labs-2017/issues/events/1108801928",
  "actor" : {
    "login" : "1414080903104",
    "id" : 26102070,
    "avatar_url" : "https://avatars0.githubusercontent.com/u/26102070?v=3",
    "gravatar_id" : "",
    "url" : "https://api.github.com/users/1414080903104",
    "html_url" : "https://github.com/1414080903104",
    "followers_url" : "https://api.github.com/users/1414080903104/followers",
    "following_url" : "https://api.github.com/users/1414080903104/following{/other_user}",
    "gists_url" : "https://api.github.com/users/1414080903104/gists{/gist_id}",
    "starred_url" : "https://api.github.com/users/1414080903104/starred{/owner}{/repo}",
    "subscriptions_url" : "https://api.github.com/users/1414080903104/subscriptions",
    "organizations_url" : "https://api.github.com/users/1414080903104/orgs",
    "repos_url" : "https://api.github.com/users/1414080903104/repos",
    "events_url" : "https://api.github.com/users/1414080903104/events{/privacy}",
    "received_events_url" : "https://api.github.com/users/1414080903104/received_events",
    "type" : "User",
    "site_admin" : false
  },
  "event" : "referenced",
  "commit_id" : "e1029f8d90cd830d7f98354d1f260bbbafa3870b",
  "commit_url" : "https://api.github.com/repos/1414080903104/android-labs-2017/commits/e1029f8d90cd830d7f98354d1f260bbbafa3870b",
  "created_at" : "2017-06-03T10:22:20Z"
}, {
  "id" : 1108844389,
  "url" : "https://api.github.com/repos/hzuapps/android-labs-2017/issues/events/1108844389",
  "actor" : {
    "login" : "AmoTF",
    "id" : 26158599,
    "avatar_url" : "https://avatars1.githubusercontent.com/u/26158599?v=3",
    "gravatar_id" : "",
    "url" : "https://api.github.com/users/AmoTF",
    "html_url" : "https://github.com/AmoTF",
    "followers_url" : "https://api.github.com/users/AmoTF/followers",
    "following_url" : "https://api.github.com/users/AmoTF/following{/other_user}",
    "gists_url" : "https://api.github.com/users/AmoTF/gists{/gist_id}",
    "starred_url" : "https://api.github.com/users/AmoTF/starred{/owner}{/repo}",
    "subscriptions_url" : "https://api.github.com/users/AmoTF/subscriptions",
    "organizations_url" : "https://api.github.com/users/AmoTF/orgs",
    "repos_url" : "https://api.github.com/users/AmoTF/repos",
    "events_url" : "https://api.github.com/users/AmoTF/events{/privacy}",
    "received_events_url" : "https://api.github.com/users/AmoTF/received_events",
    "type" : "User",
    "site_admin" : false
  },
  "event" : "referenced",
  "commit_id" : "bfeafb8d9642501cc4f863945d166dc457bf052a",
  "commit_url" : "https://api.github.com/repos/AmoTF/android-labs-2017/commits/bfeafb8d9642501cc4f863945d166dc457bf052a",
  "created_at" : "2017-06-03T13:45:14Z"
}, {
  "id" : 1111930179,
  "url" : "https://api.github.com/repos/hzuapps/android-labs-2017/issues/events/1111930179",
  "actor" : {
    "login" : "wubucheng",
    "id" : 11130313,
    "avatar_url" : "https://avatars3.githubusercontent.com/u/11130313?v=3",
    "gravatar_id" : "",
    "url" : "https://api.github.com/users/wubucheng",
    "html_url" : "https://github.com/wubucheng",
    "followers_url" : "https://api.github.com/users/wubucheng/followers",
    "following_url" : "https://api.github.com/users/wubucheng/following{/other_user}",
    "gists_url" : "https://api.github.com/users/wubucheng/gists{/gist_id}",
    "starred_url" : "https://api.github.com/users/wubucheng/starred{/owner}{/repo}",
    "subscriptions_url" : "https://api.github.com/users/wubucheng/subscriptions",
    "organizations_url" : "https://api.github.com/users/wubucheng/orgs",
    "repos_url" : "https://api.github.com/users/wubucheng/repos",
    "events_url" : "https://api.github.com/users/wubucheng/events{/privacy}",
    "received_events_url" : "https://api.github.com/users/wubucheng/received_events",
    "type" : "User",
    "site_admin" : false
  },
  "event" : "referenced",
  "commit_id" : "de1d480974b8ce54bd914c45813a200044d2d365",
  "commit_url" : "https://api.github.com/repos/wubucheng/android-labs-2017/commits/de1d480974b8ce54bd914c45813a200044d2d365",
  "created_at" : "2017-06-06T14:53:08Z"
}, {
  "id" : 1111952428,
  "url" : "https://api.github.com/repos/hzuapps/android-labs-2017/issues/events/1111952428",
  "actor" : {
    "login" : "wubucheng",
    "id" : 11130313,
    "avatar_url" : "https://avatars3.githubusercontent.com/u/11130313?v=3",
    "gravatar_id" : "",
    "url" : "https://api.github.com/users/wubucheng",
    "html_url" : "https://github.com/wubucheng",
    "followers_url" : "https://api.github.com/users/wubucheng/followers",
    "following_url" : "https://api.github.com/users/wubucheng/following{/other_user}",
    "gists_url" : "https://api.github.com/users/wubucheng/gists{/gist_id}",
    "starred_url" : "https://api.github.com/users/wubucheng/starred{/owner}{/repo}",
    "subscriptions_url" : "https://api.github.com/users/wubucheng/subscriptions",
    "organizations_url" : "https://api.github.com/users/wubucheng/orgs",
    "repos_url" : "https://api.github.com/users/wubucheng/repos",
    "events_url" : "https://api.github.com/users/wubucheng/events{/privacy}",
    "received_events_url" : "https://api.github.com/users/wubucheng/received_events",
    "type" : "User",
    "site_admin" : false
  },
  "event" : "referenced",
  "commit_id" : "e1a8e13a8a76761b0bda57ed760e90e53c4cb60d",
  "commit_url" : "https://api.github.com/repos/wubucheng/android-labs-2017/commits/e1a8e13a8a76761b0bda57ed760e90e53c4cb60d",
  "created_at" : "2017-06-06T15:03:45Z"
}, {
  "id" : 1112951715,
  "url" : "https://api.github.com/repos/hzuapps/android-labs-2017/issues/events/1112951715",
  "actor" : {
    "login" : "14w2mary",
    "id" : 26320629,
    "avatar_url" : "https://avatars2.githubusercontent.com/u/26320629?v=3",
    "gravatar_id" : "",
    "url" : "https://api.github.com/users/14w2mary",
    "html_url" : "https://github.com/14w2mary",
    "followers_url" : "https://api.github.com/users/14w2mary/followers",
    "following_url" : "https://api.github.com/users/14w2mary/following{/other_user}",
    "gists_url" : "https://api.github.com/users/14w2mary/gists{/gist_id}",
    "starred_url" : "https://api.github.com/users/14w2mary/starred{/owner}{/repo}",
    "subscriptions_url" : "https://api.github.com/users/14w2mary/subscriptions",
    "organizations_url" : "https://api.github.com/users/14w2mary/orgs",
    "repos_url" : "https://api.github.com/users/14w2mary/repos",
    "events_url" : "https://api.github.com/users/14w2mary/events{/privacy}",
    "received_events_url" : "https://api.github.com/users/14w2mary/received_events",
    "type" : "User",
    "site_admin" : false
  },
  "event" : "referenced",
  "commit_id" : "fd67e01ac1c7d1cd2ce6d155fb2b4adf6ea06721",
  "commit_url" : "https://api.github.com/repos/14w2mary/android-labs-2017/commits/fd67e01ac1c7d1cd2ce6d155fb2b4adf6ea06721",
  "created_at" : "2017-06-07T04:20:21Z"
}, {
  "id" : 1113753347,
  "url" : "https://api.github.com/repos/hzuapps/android-labs-2017/issues/events/1113753347",
  "actor" : {
    "login" : "claixiang",
    "id" : 26144470,
    "avatar_url" : "https://avatars0.githubusercontent.com/u/26144470?v=3",
    "gravatar_id" : "",
    "url" : "https://api.github.com/users/claixiang",
    "html_url" : "https://github.com/claixiang",
    "followers_url" : "https://api.github.com/users/claixiang/followers",
    "following_url" : "https://api.github.com/users/claixiang/following{/other_user}",
    "gists_url" : "https://api.github.com/users/claixiang/gists{/gist_id}",
    "starred_url" : "https://api.github.com/users/claixiang/starred{/owner}{/repo}",
    "subscriptions_url" : "https://api.github.com/users/claixiang/subscriptions",
    "organizations_url" : "https://api.github.com/users/claixiang/orgs",
    "repos_url" : "https://api.github.com/users/claixiang/repos",
    "events_url" : "https://api.github.com/users/claixiang/events{/privacy}",
    "received_events_url" : "https://api.github.com/users/claixiang/received_events",
    "type" : "User",
    "site_admin" : false
  },
  "event" : "referenced",
  "commit_id" : "156a6052be009dbbc0d08e7c55c0e9e37527b78c",
  "commit_url" : "https://api.github.com/repos/claixiang/android-labs-2017/commits/156a6052be009dbbc0d08e7c55c0e9e37527b78c",
  "created_at" : "2017-06-07T14:22:41Z"
}, {
  "id" : 1114142484,
  "url" : "https://api.github.com/repos/hzuapps/android-labs-2017/issues/events/1114142484",
  "actor" : {
    "login" : "linzihong888",
    "id" : 26339428,
    "avatar_url" : "https://avatars3.githubusercontent.com/u/26339428?v=3",
    "gravatar_id" : "",
    "url" : "https://api.github.com/users/linzihong888",
    "html_url" : "https://github.com/linzihong888",
    "followers_url" : "https://api.github.com/users/linzihong888/followers",
    "following_url" : "https://api.github.com/users/linzihong888/following{/other_user}",
    "gists_url" : "https://api.github.com/users/linzihong888/gists{/gist_id}",
    "starred_url" : "https://api.github.com/users/linzihong888/starred{/owner}{/repo}",
    "subscriptions_url" : "https://api.github.com/users/linzihong888/subscriptions",
    "organizations_url" : "https://api.github.com/users/linzihong888/orgs",
    "repos_url" : "https://api.github.com/users/linzihong888/repos",
    "events_url" : "https://api.github.com/users/linzihong888/events{/privacy}",
    "received_events_url" : "https://api.github.com/users/linzihong888/received_events",
    "type" : "User",
    "site_admin" : false
  },
  "event" : "referenced",
  "commit_id" : "c4c917e9501fb89c0e3794873fca33415cce3c9b",
  "commit_url" : "https://api.github.com/repos/linzihong888/android-labs-2017/commits/c4c917e9501fb89c0e3794873fca33415cce3c9b",
  "created_at" : "2017-06-07T17:53:26Z"
}, {
  "id" : 1115005563,
  "url" : "https://api.github.com/repos/hzuapps/android-labs-2017/issues/events/1115005563",
  "actor" : {
    "login" : "wubucheng",
    "id" : 11130313,
    "avatar_url" : "https://avatars3.githubusercontent.com/u/11130313?v=3",
    "gravatar_id" : "",
    "url" : "https://api.github.com/users/wubucheng",
    "html_url" : "https://github.com/wubucheng",
    "followers_url" : "https://api.github.com/users/wubucheng/followers",
    "following_url" : "https://api.github.com/users/wubucheng/following{/other_user}",
    "gists_url" : "https://api.github.com/users/wubucheng/gists{/gist_id}",
    "starred_url" : "https://api.github.com/users/wubucheng/starred{/owner}{/repo}",
    "subscriptions_url" : "https://api.github.com/users/wubucheng/subscriptions",
    "organizations_url" : "https://api.github.com/users/wubucheng/orgs",
    "repos_url" : "https://api.github.com/users/wubucheng/repos",
    "events_url" : "https://api.github.com/users/wubucheng/events{/privacy}",
    "received_events_url" : "https://api.github.com/users/wubucheng/received_events",
    "type" : "User",
    "site_admin" : false
  },
  "event" : "referenced",
  "commit_id" : "0e07009cb5aa818b39542afd54cffced313afaa2",
  "commit_url" : "https://api.github.com/repos/wubucheng/android-labs-2017/commits/0e07009cb5aa818b39542afd54cffced313afaa2",
  "created_at" : "2017-06-08T07:50:25Z"
}, {
  "id" : 1115095740,
  "url" : "https://api.github.com/repos/hzuapps/android-labs-2017/issues/events/1115095740",
  "actor" : {
    "login" : "HardyYao",
    "id" : 22211184,
    "avatar_url" : "https://avatars0.githubusercontent.com/u/22211184?v=3",
    "gravatar_id" : "",
    "url" : "https://api.github.com/users/HardyYao",
    "html_url" : "https://github.com/HardyYao",
    "followers_url" : "https://api.github.com/users/HardyYao/followers",
    "following_url" : "https://api.github.com/users/HardyYao/following{/other_user}",
    "gists_url" : "https://api.github.com/users/HardyYao/gists{/gist_id}",
    "starred_url" : "https://api.github.com/users/HardyYao/starred{/owner}{/repo}",
    "subscriptions_url" : "https://api.github.com/users/HardyYao/subscriptions",
    "organizations_url" : "https://api.github.com/users/HardyYao/orgs",
    "repos_url" : "https://api.github.com/users/HardyYao/repos",
    "events_url" : "https://api.github.com/users/HardyYao/events{/privacy}",
    "received_events_url" : "https://api.github.com/users/HardyYao/received_events",
    "type" : "User",
    "site_admin" : false
  },
  "event" : "referenced",
  "commit_id" : "1b23edd4df47822c982ff5c7eaae312125da0030",
  "commit_url" : "https://api.github.com/repos/HardyYao/android-labs-2017/commits/1b23edd4df47822c982ff5c7eaae312125da0030",
  "created_at" : "2017-06-08T08:52:40Z"
}, {
  "id" : 1115110730,
  "url" : "https://api.github.com/repos/hzuapps/android-labs-2017/issues/events/1115110730",
  "actor" : {
    "login" : "HardyYao",
    "id" : 22211184,
    "avatar_url" : "https://avatars0.githubusercontent.com/u/22211184?v=3",
    "gravatar_id" : "",
    "url" : "https://api.github.com/users/HardyYao",
    "html_url" : "https://github.com/HardyYao",
    "followers_url" : "https://api.github.com/users/HardyYao/followers",
    "following_url" : "https://api.github.com/users/HardyYao/following{/other_user}",
    "gists_url" : "https://api.github.com/users/HardyYao/gists{/gist_id}",
    "starred_url" : "https://api.github.com/users/HardyYao/starred{/owner}{/repo}",
    "subscriptions_url" : "https://api.github.com/users/HardyYao/subscriptions",
    "organizations_url" : "https://api.github.com/users/HardyYao/orgs",
    "repos_url" : "https://api.github.com/users/HardyYao/repos",
    "events_url" : "https://api.github.com/users/HardyYao/events{/privacy}",
    "received_events_url" : "https://api.github.com/users/HardyYao/received_events",
    "type" : "User",
    "site_admin" : false
  },
  "event" : "referenced",
  "commit_id" : "513ce42a8dbcd33dc5d155ced045f16273e5f2ce",
  "commit_url" : "https://api.github.com/repos/HardyYao/android-labs-2017/commits/513ce42a8dbcd33dc5d155ced045f16273e5f2ce",
  "created_at" : "2017-06-08T09:02:05Z"
}, {
  "id" : 1115424868,
  "url" : "https://api.github.com/repos/hzuapps/android-labs-2017/issues/events/1115424868",
  "actor" : {
    "login" : "LouQingYi",
    "id" : 26144251,
    "avatar_url" : "https://avatars1.githubusercontent.com/u/26144251?v=3",
    "gravatar_id" : "",
    "url" : "https://api.github.com/users/LouQingYi",
    "html_url" : "https://github.com/LouQingYi",
    "followers_url" : "https://api.github.com/users/LouQingYi/followers",
    "following_url" : "https://api.github.com/users/LouQingYi/following{/other_user}",
    "gists_url" : "https://api.github.com/users/LouQingYi/gists{/gist_id}",
    "starred_url" : "https://api.github.com/users/LouQingYi/starred{/owner}{/repo}",
    "subscriptions_url" : "https://api.github.com/users/LouQingYi/subscriptions",
    "organizations_url" : "https://api.github.com/users/LouQingYi/orgs",
    "repos_url" : "https://api.github.com/users/LouQingYi/repos",
    "events_url" : "https://api.github.com/users/LouQingYi/events{/privacy}",
    "received_events_url" : "https://api.github.com/users/LouQingYi/received_events",
    "type" : "User",
    "site_admin" : false
  },
  "event" : "referenced",
  "commit_id" : "c5cfd375aea993d3d3a57efbabe3013bfb1aedd4",
  "commit_url" : "https://api.github.com/repos/LouQingYi/android-labs-2017/commits/c5cfd375aea993d3d3a57efbabe3013bfb1aedd4",
  "created_at" : "2017-06-08T12:42:55Z"
}, {
  "id" : 1115432861,
  "url" : "https://api.github.com/repos/hzuapps/android-labs-2017/issues/events/1115432861",
  "actor" : {
    "login" : "HardyYao",
    "id" : 22211184,
    "avatar_url" : "https://avatars0.githubusercontent.com/u/22211184?v=3",
    "gravatar_id" : "",
    "url" : "https://api.github.com/users/HardyYao",
    "html_url" : "https://github.com/HardyYao",
    "followers_url" : "https://api.github.com/users/HardyYao/followers",
    "following_url" : "https://api.github.com/users/HardyYao/following{/other_user}",
    "gists_url" : "https://api.github.com/users/HardyYao/gists{/gist_id}",
    "starred_url" : "https://api.github.com/users/HardyYao/starred{/owner}{/repo}",
    "subscriptions_url" : "https://api.github.com/users/HardyYao/subscriptions",
    "organizations_url" : "https://api.github.com/users/HardyYao/orgs",
    "repos_url" : "https://api.github.com/users/HardyYao/repos",
    "events_url" : "https://api.github.com/users/HardyYao/events{/privacy}",
    "received_events_url" : "https://api.github.com/users/HardyYao/received_events",
    "type" : "User",
    "site_admin" : false
  },
  "event" : "referenced",
  "commit_id" : "4e7dc66ed23d7187c32c38d503fa236ba8ab0788",
  "commit_url" : "https://api.github.com/repos/HardyYao/android-labs-2017/commits/4e7dc66ed23d7187c32c38d503fa236ba8ab0788",
  "created_at" : "2017-06-08T12:48:05Z"
}, {
  "id" : 1115585102,
  "url" : "https://api.github.com/repos/hzuapps/android-labs-2017/issues/events/1115585102",
  "actor" : {
    "login" : "HardyYao",
    "id" : 22211184,
    "avatar_url" : "https://avatars0.githubusercontent.com/u/22211184?v=3",
    "gravatar_id" : "",
    "url" : "https://api.github.com/users/HardyYao",
    "html_url" : "https://github.com/HardyYao",
    "followers_url" : "https://api.github.com/users/HardyYao/followers",
    "following_url" : "https://api.github.com/users/HardyYao/following{/other_user}",
    "gists_url" : "https://api.github.com/users/HardyYao/gists{/gist_id}",
    "starred_url" : "https://api.github.com/users/HardyYao/starred{/owner}{/repo}",
    "subscriptions_url" : "https://api.github.com/users/HardyYao/subscriptions",
    "organizations_url" : "https://api.github.com/users/HardyYao/orgs",
    "repos_url" : "https://api.github.com/users/HardyYao/repos",
    "events_url" : "https://api.github.com/users/HardyYao/events{/privacy}",
    "received_events_url" : "https://api.github.com/users/HardyYao/received_events",
    "type" : "User",
    "site_admin" : false
  },
  "event" : "referenced",
  "commit_id" : "5fee90e52203a4610f6a1fb6f113ba6cb6d04424",
  "commit_url" : "https://api.github.com/repos/HardyYao/android-labs-2017/commits/5fee90e52203a4610f6a1fb6f113ba6cb6d04424",
  "created_at" : "2017-06-08T14:13:07Z"
}, {
  "id" : 1118180432,
  "url" : "https://api.github.com/repos/hzuapps/android-labs-2017/issues/events/1118180432",
  "actor" : {
    "login" : "ileyinan",
    "id" : 26106952,
    "avatar_url" : "https://avatars2.githubusercontent.com/u/26106952?v=3",
    "gravatar_id" : "",
    "url" : "https://api.github.com/users/ileyinan",
    "html_url" : "https://github.com/ileyinan",
    "followers_url" : "https://api.github.com/users/ileyinan/followers",
    "following_url" : "https://api.github.com/users/ileyinan/following{/other_user}",
    "gists_url" : "https://api.github.com/users/ileyinan/gists{/gist_id}",
    "starred_url" : "https://api.github.com/users/ileyinan/starred{/owner}{/repo}",
    "subscriptions_url" : "https://api.github.com/users/ileyinan/subscriptions",
    "organizations_url" : "https://api.github.com/users/ileyinan/orgs",
    "repos_url" : "https://api.github.com/users/ileyinan/repos",
    "events_url" : "https://api.github.com/users/ileyinan/events{/privacy}",
    "received_events_url" : "https://api.github.com/users/ileyinan/received_events",
    "type" : "User",
    "site_admin" : false
  },
  "event" : "referenced",
  "commit_id" : "61b7ac203630058ade9569a1fe0c6c066d11e169",
  "commit_url" : "https://api.github.com/repos/ileyinan/android-labs-2017/commits/61b7ac203630058ade9569a1fe0c6c066d11e169",
  "created_at" : "2017-06-10T08:20:33Z"
}, {
  "id" : 1118213453,
  "url" : "https://api.github.com/repos/hzuapps/android-labs-2017/issues/events/1118213453",
  "actor" : {
    "login" : "liuzezhao",
    "id" : 26058246,
    "avatar_url" : "https://avatars2.githubusercontent.com/u/26058246?v=3",
    "gravatar_id" : "",
    "url" : "https://api.github.com/users/liuzezhao",
    "html_url" : "https://github.com/liuzezhao",
    "followers_url" : "https://api.github.com/users/liuzezhao/followers",
    "following_url" : "https://api.github.com/users/liuzezhao/following{/other_user}",
    "gists_url" : "https://api.github.com/users/liuzezhao/gists{/gist_id}",
    "starred_url" : "https://api.github.com/users/liuzezhao/starred{/owner}{/repo}",
    "subscriptions_url" : "https://api.github.com/users/liuzezhao/subscriptions",
    "organizations_url" : "https://api.github.com/users/liuzezhao/orgs",
    "repos_url" : "https://api.github.com/users/liuzezhao/repos",
    "events_url" : "https://api.github.com/users/liuzezhao/events{/privacy}",
    "received_events_url" : "https://api.github.com/users/liuzezhao/received_events",
    "type" : "User",
    "site_admin" : false
  },
  "event" : "referenced",
  "commit_id" : "4ba94a0bf3dda4790592fef0515b31315ad9f5c9",
  "commit_url" : "https://api.github.com/repos/liuzezhao/android-labs-2017/commits/4ba94a0bf3dda4790592fef0515b31315ad9f5c9",
  "created_at" : "2017-06-10T11:10:44Z"
}, {
  "id" : 1118222323,
  "url" : "https://api.github.com/repos/hzuapps/android-labs-2017/issues/events/1118222323",
  "actor" : {
    "login" : "ileyinan",
    "id" : 26106952,
    "avatar_url" : "https://avatars2.githubusercontent.com/u/26106952?v=3",
    "gravatar_id" : "",
    "url" : "https://api.github.com/users/ileyinan",
    "html_url" : "https://github.com/ileyinan",
    "followers_url" : "https://api.github.com/users/ileyinan/followers",
    "following_url" : "https://api.github.com/users/ileyinan/following{/other_user}",
    "gists_url" : "https://api.github.com/users/ileyinan/gists{/gist_id}",
    "starred_url" : "https://api.github.com/users/ileyinan/starred{/owner}{/repo}",
    "subscriptions_url" : "https://api.github.com/users/ileyinan/subscriptions",
    "organizations_url" : "https://api.github.com/users/ileyinan/orgs",
    "repos_url" : "https://api.github.com/users/ileyinan/repos",
    "events_url" : "https://api.github.com/users/ileyinan/events{/privacy}",
    "received_events_url" : "https://api.github.com/users/ileyinan/received_events",
    "type" : "User",
    "site_admin" : false
  },
  "event" : "referenced",
  "commit_id" : "4a3c83bf2ab603950089b3037896614f15fe0792",
  "commit_url" : "https://api.github.com/repos/ileyinan/android-labs-2017/commits/4a3c83bf2ab603950089b3037896614f15fe0792",
  "created_at" : "2017-06-10T11:54:26Z"
} ]